<annotation verified="no">
  <folder>train</folder>
  <filename>0019.jpg</filename>
  <path>/home/linyong/train/0019.jpg</path>
  <source>
    <database>Unknown</database>
  </source>
  <size>
    <width>768</width>
    <height>1024</height>
    <depth>3</depth>
  </size>
  <segmented>0</segmented>
  <object>
    <name>monkey</name>
    <pose>Unspecified</pose>
    <truncated>0</truncated>
    <difficult>0</difficult>
    <bndbox>
      <xmin>32</xmin>
      <ymin>321</ymin>
      <xmax>397</xmax>
      <ymax>823</ymax>
    </bndbox>
  </object>
  <object>
    <name>monkey</name>
    <pose>Unspecified</pose>
    <truncated>0</truncated>
    <difficult>0</difficult>
    <bndbox>
      <xmin>127</xmin>
      <ymin>164</ymin>
      <xmax>616</xmax>
      <ymax>717</ymax>
    </bndbox>
  </object>
</annotation>
